odoo/addons/shopinvader_sale_automatic_workflow/README.rst
odoo/addons/shopinvader_sale_automatic_workflow/__init__.py
odoo/addons/shopinvader_sale_automatic_workflow/__manifest__.py
odoo/addons/shopinvader_sale_automatic_workflow/i18n/shopinvader_sale_automatic_workflow.pot
odoo/addons/shopinvader_sale_automatic_workflow/models/__init__.py
odoo/addons/shopinvader_sale_automatic_workflow/models/shopinvader_backend.py
odoo/addons/shopinvader_sale_automatic_workflow/readme/CONTRIBUTORS.rst
odoo/addons/shopinvader_sale_automatic_workflow/readme/DESCRIPTION.rst
odoo/addons/shopinvader_sale_automatic_workflow/services/__init__.py
odoo/addons/shopinvader_sale_automatic_workflow/services/cart.py
odoo/addons/shopinvader_sale_automatic_workflow/static/description/index.html
odoo/addons/shopinvader_sale_automatic_workflow/tests/__init__.py
odoo/addons/shopinvader_sale_automatic_workflow/tests/test_automatic_workflow.py
odoo/addons/shopinvader_sale_automatic_workflow/views/shopinvader_backend.xml
odoo14_addon_shopinvader_sale_automatic_workflow-14.0.1.1.0.dist-info/METADATA
odoo14_addon_shopinvader_sale_automatic_workflow-14.0.1.1.0.dist-info/WHEEL
odoo14_addon_shopinvader_sale_automatic_workflow-14.0.1.1.0.dist-info/top_level.txt
odoo14_addon_shopinvader_sale_automatic_workflow-14.0.1.1.0.dist-info/RECORD
